natinterp3d-0.1.0.dist-info/top_level.txt
natinterp3d-0.1.0.dist-info/RECORD
natinterp3d-0.1.0.dist-info/LICENSE
natinterp3d-0.1.0.dist-info/METADATA
natinterp3d-0.1.0.dist-info/WHEEL
natinterp3d/natural.c
natinterp3d/utils.c
natinterp3d/utils.h
natinterp3d/predicates.c
natinterp3d/natinterp3d_cython.pyx
natinterp3d/natinterp3d_cython.cpython-312-x86_64-linux-gnu.so
natinterp3d/natural.h
natinterp3d/natinterp3d_main.py
natinterp3d/__init__.py
natinterp3d/delaunay.c
natinterp3d/kdtree.c
natinterp3d/example.c
natinterp3d/kdtree.h
natinterp3d/delaunay.h
natinterp3d.libs/libgomp-a34b3233.so.1.0.0
