Metadata-Version: 2.1
Name: natinterp3d
Version: 0.1.0
Summary: Natural Neighbor Interpolation in 3D
Author-email: István Sárándi <istvan.sarandi@uni-tuebingen.de>
License:                     GNU GENERAL PUBLIC LICENSE
Requires-Python: >=3.6
License-File: LICENSE
Requires-Dist: numpy
Requires-Dist: scipy
